<?xml version="1.0" encoding="UTF-8"?>
<metadata xml:lang="en"><Esri><CreaDate>20160502</CreaDate><CreaTime>15002300</CreaTime><ArcGISFormat>1.0</ArcGISFormat><ArcGISstyle>XTools Pro Metadata</ArcGISstyle><SyncOnce>TRUE</SyncOnce><DataProperties><lineage><Process ToolSource="C:\Program Files (x86)\ArcGIS\Desktop10.0\ArcToolbox\Toolboxes\Data Management Tools.tbx\CalculateField" Date="20120710" Time="143504">CalculateField Aeropuerto_Origen_Destino Ciudad "Maracaibo" VB #</Process><Process ToolSource="C:\Program Files (x86)\ArcGIS\Desktop10.0\ArcToolbox\Toolboxes\Data Management Tools.tbx\CalculateField" Date="20120710" Time="143548">CalculateField Aeropuerto_Origen_Destino Ciudad "Maiquetia" VB #</Process><Process ToolSource="C:\Program Files (x86)\ArcGIS\Desktop10.0\ArcToolbox\Toolboxes\Data Management Tools.tbx\CalculateField" Date="20120710" Time="143645">CalculateField Aeropuerto_Origen_Destino Ciudad "Porlamar" VB #</Process><Process ToolSource="C:\Program Files (x86)\ArcGIS\Desktop10.0\ArcToolbox\Toolboxes\Data Management Tools.tbx\CalculateField" Date="20120710" Time="143701">CalculateField Aeropuerto_Origen_Destino Ciudad "Maturin" VB #</Process><Process ToolSource="C:\Program Files (x86)\ArcGIS\Desktop10.0\ArcToolbox\Toolboxes\Data Management Tools.tbx\CalculateField" Date="20130817" Time="144244">CalculateField "Aeropuerto Origen-Destino" Ciudad "Ciudad Bolívar" VB #</Process><Process ToolSource="c:\program files (x86)\arcgis\desktop10.3\ArcToolbox\Toolboxes\Data Management Tools.tbx\CalculateField" Date="20160501" Time="222308">CalculateField Aeropuertos Tipo "Internacional" VB #</Process><Process ToolSource="c:\program files (x86)\arcgis\desktop10.3\ArcToolbox\Toolboxes\Data Management Tools.tbx\CalculateField" Date="20160501" Time="222343">CalculateField Aeropuertos Tipo "Nacional" VB #</Process></lineage></DataProperties></Esri></metadata>
